MANIFEST.in
README.md
setup.cfg
setup.py
string_distance/__init__.py
string_distance/bm25.py
string_distance/cost.pxd
string_distance/edit_distance.c
string_distance/edit_distance.pyx
string_distance/float_cost.pxd
string_distance/float_edit_distance.c
string_distance/float_edit_distance.pyx
string_distance/float_minimum_edit_distance.c
string_distance/float_minimum_edit_distance.pxd
string_distance/float_minimum_edit_distance.pyx
string_distance/maximum_edit_distance.c
string_distance/maximum_edit_distance.pxd
string_distance/maximum_edit_distance.pyx
string_distance/minimum_edit_distance.c
string_distance/minimum_edit_distance.pxd
string_distance/minimum_edit_distance.pyx
string_distance/sequence_distance.c
string_distance/sequence_distance.pxd
string_distance/sequence_distance.pyx
string_distance/tests.py
string_distance/token_distance.c
string_distance/token_distance.pyx
string_distance.egg-info/PKG-INFO
string_distance.egg-info/SOURCES.txt
string_distance.egg-info/dependency_links.txt
string_distance.egg-info/requires.txt
string_distance.egg-info/top_level.txt