Metadata-Version: 2.1
Name: string-distance
Version: 0.3.2
Summary: Minimum Edit Distance
Home-page: https://github.com/blester125/string_distance
Author: blester125
Author-email: blester125@gmail.com
License: MIT
Download-URL: https://github.com/blester125/string_distance/archive/0.3.2.tar.gz
Platform: UNKNOWN
Requires-Python: >=3.5
Provides-Extra: test
